{"lastUsed":1629286373623,"path":"D:\/workspace-curso-java","projectCount":2,"recentFiles":[{"path":"\/vector\/src\/main\/java\/br\/com\/vector\/cfrdocarmo\/config\/security","parentWorkspace":"D:\/workspace-curso-java","name":"DevSecurityConfigurations.java","lastModified":1629286234695,"locationURI":"file:\/D:\/workspace-curso-java\/vector\/src\/main\/java\/br\/com\/vector\/cfrdocarmo\/config\/security\/DevSecurityConfigurations.java"},{"path":"\/vector\/src\/main\/resources","parentWorkspace":"D:\/workspace-curso-java","name":"application.properties","lastModified":1629285924150,"locationURI":"file:\/D:\/workspace-curso-java\/vector\/src\/main\/resources\/application.properties"}]}